binaryen/internals.py
binaryen/__type_builder.py
binaryen/__module.py
binaryen/literal.py
binaryen/__feature.py
binaryen/__init__.py
binaryen/operations.py
binaryen/__expression.py
binaryen/_binaryen.abi3.so
binaryen/__functionref.py
binaryen/__global.py
binaryen/expression.py
binaryen/type/struct_type.py
binaryen/type/__init__.py
binaryen/type/heap_type.py
binaryen/type/signature_type.py
binaryen/type/array_type.py
binaryen/type/to_str.py
binaryen.py-117.1.1.dist-info/RECORD
binaryen.py-117.1.1.dist-info/LICENSE
binaryen.py-117.1.1.dist-info/WHEEL
binaryen.py-117.1.1.dist-info/top_level.txt
binaryen.py-117.1.1.dist-info/METADATA
