Metadata-Version: 2.1
Name: binaryen.py
Version: 117.1.1
Summary: A Python wrapper for Binaryen
Author-email: Jonathan Hargreaves <jhargreaves189@gmail.com>
License:                                  Apache License
Project-URL: Source Code, https://github.com/jonathanharg/binaryen.py
Project-URL: Issues, https://github.com/jonathanharg/binaryen.py/issues
Project-URL: Original Source Code, https://github.com/WebAssembly/binaryen
Keywords: WebAssembly,Wasm,Binaryen,binaryen.py
Classifier: Environment :: MacOS X
Classifier: Environment :: WebAssembly
Classifier: Environment :: WebAssembly :: WASI
Classifier: Environment :: Win32 (MS Windows)
Classifier: Intended Audience :: Developers
Classifier: License :: OSI Approved :: Apache Software License
Classifier: Natural Language :: English
Classifier: Operating System :: MacOS
Classifier: Operating System :: Microsoft :: Windows
Classifier: Operating System :: POSIX :: Linux
Classifier: Programming Language :: Assembly
Classifier: Programming Language :: Python
Classifier: Topic :: Software Development :: Compilers
Requires-Python: >=3.12
License-File: LICENSE
Requires-Dist: cffi>=1.15.0
Provides-Extra: dev
Requires-Dist: black; extra == "dev"
Requires-Dist: isort; extra == "dev"
Requires-Dist: cibuildwheel; extra == "dev"
